{
  "created_at": "2026-04-16T11:04:10",
  "output_dir": "outputs\\experiment_20260416_110110",
  "config": {
    "seed": 42,
    "data": {
      "source": "mt5",
      "symbol": "USTEC.r",
      "timeframe": "M15",
      "n_bars": 20000,
      "csv_path": null
    },
    "features": {
      "feature_mode": "causal_v3",
      "swing_window": 5,
      "horizon": 15,
      "atr_mult": 1.0,
      "min_activation": 0.1
    },
    "walk_forward": {
      "initial_train": 8000,
      "val_size": 2000,
      "test_size": 2000,
      "step_size": 2000,
      "max_folds": 4
    },
    "training": {
      "epochs": 160,
      "batch_size": 256,
      "learning_rate": 0.002,
      "consequent_lr_mult": 5.0,
      "weight_decay": 0.0001,
      "grad_clip": 1.0,
      "lambda_mf": 0.0,
      "sigma_min": 0.05,
      "scheduler_patience": 5,
      "scheduler_factor": 0.5,
      "early_stop_patience": 15,
      "min_delta": 1e-06,
      "min_lr": 1e-06,
      "log_every": 10,
      "device": "cpu"
    },
    "threshold": {
      "candidates": [
        0.03,
        0.05,
        0.07,
        0.1
      ],
      "min_activations_directional": 80,
      "min_trades_backtest": 60
    },
    "backtest": {
      "initial_capital": 100000.0,
      "risk_per_trade": 0.01,
      "reward_to_risk": 1.0,
      "stop_mode": "atr",
      "max_holding_bars": 15
    },
    "metrics": {
      "zero_tolerance": 0.0
    },
    "outputs": {
      "root": "outputs",
      "prefix": "experiment",
      "save_models": true
    }
  },
  "aggregate": {
    "mean_train_samples": 11000.0,
    "mean_val_samples": 2000.0,
    "mean_test_samples": 2000.0,
    "mean_test_score_target_corr": 0.016468517905089946,
    "mean_test_score_mean": 0.009532546799164265,
    "mean_test_score_std": 0.08098036237061024,
    "mean_test_rule_dominance": 0.4196039214730263,
    "mean_test_active_rules_95": 3.75,
    "mean_thresholded_test_directional_accuracy": 0.525955626195678,
    "mean_thresholded_test_coverage": 0.381375,
    "mean_thresholded_test_activated": 762.75,
    "mean_test_total_trades": 270.75,
    "mean_test_profit_factor": 0.9121287475218579,
    "mean_test_win_rate": 47.86696198641407,
    "mean_test_total_return": -9.615979875144184,
    "mean_test_max_drawdown": 20.51290489306952,
    "mean_test_sharpe_ratio": -2.661379556966143,
    "mean_test_sortino_ratio": -2.52264153400699,
    "mean_test_calmar_ratio": -2.2286332873349624,
    "mean_test_sqn": -0.6270155215660088,
    "mean_train_n_samples": 11000.0,
    "mean_train_n_directional_samples": 11000.0,
    "mean_train_mae": 0.9255561935531302,
    "mean_train_rmse": 0.9343331391318805,
    "mean_train_r2": 0.004523348275264655,
    "mean_train_directional_accuracy": 0.5318934523809524,
    "mean_train_weighted_hit_rate": 0.5309545265025934,
    "mean_val_n_samples": 2000.0,
    "mean_val_n_directional_samples": 2000.0,
    "mean_val_mae": 0.9330997174871534,
    "mean_val_rmse": 0.9407573058921506,
    "mean_val_r2": -0.003838826711059923,
    "mean_val_directional_accuracy": 0.50175,
    "mean_val_weighted_hit_rate": 0.5020638688696732,
    "mean_test_n_samples": 2000.0,
    "mean_test_n_directional_samples": 2000.0,
    "mean_test_mae": 0.93505555087435,
    "mean_test_rmse": 0.9431026931239804,
    "mean_test_r2": -0.008980734076820485,
    "mean_test_directional_accuracy": 0.501,
    "mean_test_weighted_hit_rate": 0.5018481744337258,
    "folds": 4,
    "positive_pf_folds": 0,
    "positive_return_folds": 0
  },
  "folds": [
    {
      "fold": 1,
      "seed": 43,
      "train_samples": 8000,
      "val_samples": 2000,
      "test_samples": 2000,
      "train_start_time": "2025-06-11 01:15:00",
      "train_end_time": "2025-10-15 16:30:00",
      "val_start_time": "2025-10-15 16:45:00",
      "val_end_time": "2025-11-17 04:30:00",
      "test_start_time": "2025-11-17 05:15:00",
      "test_end_time": "2025-12-19 04:15:00",
      "epochs_ran": 25,
      "best_val_loss": 0.87595334649086,
      "last_lr": 0.0005,
      "directional_threshold": 0.05,
      "selected_threshold": 0.05,
      "selected_threshold_source": "directional_fallback",
      "learning_plot": "outputs\\experiment_20260416_110110\\fold_01_learning_curve.png",
      "error_plot": "outputs\\experiment_20260416_110110\\fold_01_train_val_errors.png",
      "model_path": "outputs\\experiment_20260416_110110\\fold_01_model.pt",
      "test_score_target_corr": 0.04794511792869421,
      "test_score_mean": 0.044987596571445465,
      "test_score_std": 0.08533885329961777,
      "test_rule_dominance": 0.2443348467350006,
      "test_active_rules_95": 6,
      "thresholded_test_directional_accuracy": 0.5167785234899329,
      "thresholded_test_coverage": 0.6705,
      "thresholded_test_activated": 1341,
      "test_total_trades": 431,
      "test_profit_factor": 0.9986273391457124,
      "test_win_rate": 50.11600928074246,
      "test_total_return": -0.13058714636553487,
      "test_max_drawdown": 17.544105308566092,
      "test_sharpe_ratio": 0.4120676951537912,
      "test_sortino_ratio": 0.5345196142642464,
      "test_calmar_ratio": -0.08449287405448203,
      "test_sqn": 0.08803488229094594,
      "test_trades_path": "outputs\\experiment_20260416_110110\\fold_01_trades.csv",
      "test_equity_path": "outputs\\experiment_20260416_110110\\fold_01_equity.csv",
      "train_n_samples": 8000,
      "train_n_directional_samples": 8000,
      "train_mae": 0.9208708656354783,
      "train_rmse": 0.9307558919438732,
      "train_r2": 0.009126825748175915,
      "train_directional_accuracy": 0.54025,
      "train_weighted_hit_rate": 0.5387118397872761,
      "val_n_samples": 2000,
      "val_n_directional_samples": 2000,
      "val_mae": 0.92791347075861,
      "val_rmse": 0.935927285073165,
      "val_r2": 0.007548476422048034,
      "val_directional_accuracy": 0.5375,
      "val_weighted_hit_rate": 0.5349232726851436,
      "test_n_samples": 2000,
      "test_n_directional_samples": 2000,
      "test_mae": 0.9304554616479399,
      "test_rmse": 0.9408418120240019,
      "test_r2": -0.0066030088534638764,
      "test_directional_accuracy": 0.504,
      "test_weighted_hit_rate": 0.5026010071508927,
      "diagnostics_path": "outputs\\experiment_20260416_110110\\fold_01_diagnostics.json"
    },
    {
      "fold": 2,
      "seed": 44,
      "train_samples": 10000,
      "val_samples": 2000,
      "test_samples": 2000,
      "train_start_time": "2025-06-11 01:15:00",
      "train_end_time": "2025-11-17 04:30:00",
      "val_start_time": "2025-11-17 05:15:00",
      "val_end_time": "2025-12-19 04:15:00",
      "test_start_time": "2025-12-19 04:30:00",
      "test_end_time": "2026-01-23 04:30:00",
      "epochs_ran": 21,
      "best_val_loss": 0.8822187706828117,
      "last_lr": 0.0005,
      "directional_threshold": 0.05,
      "selected_threshold": 0.1,
      "selected_threshold_source": "backtest",
      "learning_plot": "outputs\\experiment_20260416_110110\\fold_02_learning_curve.png",
      "error_plot": "outputs\\experiment_20260416_110110\\fold_02_train_val_errors.png",
      "model_path": "outputs\\experiment_20260416_110110\\fold_02_model.pt",
      "test_score_target_corr": -0.03770114701741978,
      "test_score_mean": 0.005745765753090382,
      "test_score_std": 0.08674359321594238,
      "test_rule_dominance": 0.4795038104057312,
      "test_active_rules_95": 2,
      "thresholded_test_directional_accuracy": 0.551440329218107,
      "thresholded_test_coverage": 0.1215,
      "thresholded_test_activated": 243,
      "test_total_trades": 105,
      "test_profit_factor": 0.9557733207370374,
      "test_win_rate": 49.523809523809526,
      "test_total_return": -2.3450217439001717,
      "test_max_drawdown": 10.820708721682411,
      "test_sharpe_ratio": -0.7381469960853693,
      "test_sortino_ratio": -0.48525494609913916,
      "test_calmar_ratio": -2.0271778930361712,
      "test_sqn": -0.1808198451221983,
      "test_trades_path": "outputs\\experiment_20260416_110110\\fold_02_trades.csv",
      "test_equity_path": "outputs\\experiment_20260416_110110\\fold_02_equity.csv",
      "train_n_samples": 10000,
      "train_n_directional_samples": 10000,
      "train_mae": 0.9228725820461572,
      "train_rmse": 0.9319561313576102,
      "train_r2": 0.009417162915355437,
      "train_directional_accuracy": 0.5438,
      "train_weighted_hit_rate": 0.5428301176931618,
      "val_n_samples": 2000,
      "val_n_directional_samples": 2000,
      "val_mae": 0.9295419166479841,
      "val_rmse": 0.939556467717868,
      "val_r2": -0.0038545177970348288,
      "val_directional_accuracy": 0.518,
      "val_weighted_hit_rate": 0.5175161672593145,
      "test_n_samples": 2000,
      "test_n_directional_samples": 2000,
      "test_mae": 0.9401301000152598,
      "test_rmse": 0.9474655304919009,
      "test_r2": -0.016251765826815978,
      "test_directional_accuracy": 0.466,
      "test_weighted_hit_rate": 0.4667776061722909,
      "diagnostics_path": "outputs\\experiment_20260416_110110\\fold_02_diagnostics.json"
    },
    {
      "fold": 3,
      "seed": 45,
      "train_samples": 12000,
      "val_samples": 2000,
      "test_samples": 2000,
      "train_start_time": "2025-06-11 01:15:00",
      "train_end_time": "2025-12-19 04:15:00",
      "val_start_time": "2025-12-19 04:30:00",
      "val_end_time": "2026-01-23 04:30:00",
      "test_start_time": "2026-01-23 04:45:00",
      "test_end_time": "2026-02-24 16:30:00",
      "epochs_ran": 16,
      "best_val_loss": 0.8927041366696358,
      "last_lr": 0.0005,
      "directional_threshold": 0.1,
      "selected_threshold": 0.1,
      "selected_threshold_source": "directional_fallback",
      "learning_plot": "outputs\\experiment_20260416_110110\\fold_03_learning_curve.png",
      "error_plot": "outputs\\experiment_20260416_110110\\fold_03_train_val_errors.png",
      "model_path": "outputs\\experiment_20260416_110110\\fold_03_model.pt",
      "test_score_target_corr": -0.004615767306083241,
      "test_score_mean": -0.002318666549399495,
      "test_score_std": 0.10130005329847336,
      "test_rule_dominance": 0.43672919273376465,
      "test_active_rules_95": 4,
      "thresholded_test_directional_accuracy": 0.5059101654846335,
      "thresholded_test_coverage": 0.2115,
      "thresholded_test_activated": 423,
      "test_total_trades": 163,
      "test_profit_factor": 0.7893811143147624,
      "test_win_rate": 44.171779141104295,
      "test_total_return": -18.085275098803802,
      "test_max_drawdown": 23.505067731942688,
      "test_sharpe_ratio": -6.483067637227239,
      "test_sortino_ratio": -5.261574536801189,
      "test_calmar_ratio": -3.8027036319250396,
      "test_sqn": -1.5057219236593675,
      "test_trades_path": "outputs\\experiment_20260416_110110\\fold_03_trades.csv",
      "test_equity_path": "outputs\\experiment_20260416_110110\\fold_03_equity.csv",
      "train_n_samples": 12000,
      "train_n_directional_samples": 12000,
      "train_mae": 0.9282878356590105,
      "train_rmse": 0.9383271099769684,
      "train_r2": -0.00296750158798309,
      "train_directional_accuracy": 0.5246666666666666,
      "train_weighted_hit_rate": 0.5242610709598197,
      "val_n_samples": 2000,
      "val_n_directional_samples": 2000,
      "val_mae": 0.9374926593101527,
      "val_rmse": 0.9449219518318809,
      "val_r2": -0.010802603886436613,
      "val_directional_accuracy": 0.467,
      "val_weighted_hit_rate": 0.4682341268290248,
      "test_n_samples": 2000,
      "test_n_directional_samples": 2000,
      "test_mae": 0.9361066133652712,
      "test_rmse": 0.9452036156904602,
      "test_r2": -0.013773648858739884,
      "test_directional_accuracy": 0.497,
      "test_weighted_hit_rate": 0.4994335665213341,
      "diagnostics_path": "outputs\\experiment_20260416_110110\\fold_03_diagnostics.json"
    },
    {
      "fold": 4,
      "seed": 46,
      "train_samples": 14000,
      "val_samples": 2000,
      "test_samples": 2000,
      "train_start_time": "2025-06-11 01:15:00",
      "train_end_time": "2026-01-23 04:30:00",
      "val_start_time": "2026-01-23 04:45:00",
      "val_end_time": "2026-02-24 16:30:00",
      "test_start_time": "2026-02-24 16:45:00",
      "test_end_time": "2026-03-27 05:45:00",
      "epochs_ran": 17,
      "best_val_loss": 0.8897008895874023,
      "last_lr": 0.0005,
      "directional_threshold": 0.1,
      "selected_threshold": 0.03,
      "selected_threshold_source": "backtest",
      "learning_plot": "outputs\\experiment_20260416_110110\\fold_04_learning_curve.png",
      "error_plot": "outputs\\experiment_20260416_110110\\fold_04_train_val_errors.png",
      "model_path": "outputs\\experiment_20260416_110110\\fold_04_model.pt",
      "test_score_target_corr": 0.06024586801516859,
      "test_score_mean": -0.01028450857847929,
      "test_score_std": 0.05053894966840744,
      "test_rule_dominance": 0.5178478360176086,
      "test_active_rules_95": 3,
      "thresholded_test_directional_accuracy": 0.5296934865900383,
      "thresholded_test_coverage": 0.522,
      "thresholded_test_activated": 1044,
      "test_total_trades": 384,
      "test_profit_factor": 0.9047332158899192,
      "test_win_rate": 47.65625,
      "test_total_return": -17.90303551150723,
      "test_max_drawdown": 30.18173781008689,
      "test_sharpe_ratio": -3.836371289705755,
      "test_sortino_ratio": -4.878256267391877,
      "test_calmar_ratio": -3.0001587503241565,
      "test_sqn": -0.9095551997734153,
      "test_trades_path": "outputs\\experiment_20260416_110110\\fold_04_trades.csv",
      "test_equity_path": "outputs\\experiment_20260416_110110\\fold_04_equity.csv",
      "train_n_samples": 14000,
      "train_n_directional_samples": 14000,
      "train_mae": 0.9301934908718748,
      "train_rmse": 0.9362934232490698,
      "train_r2": 0.002516906025510357,
      "train_directional_accuracy": 0.5188571428571429,
      "train_weighted_hit_rate": 0.5180150775701161,
      "val_n_samples": 2000,
      "val_n_directional_samples": 2000,
      "val_mae": 0.9374508232318667,
      "val_rmse": 0.9426235189456882,
      "val_r2": -0.008246661582816284,
      "val_directional_accuracy": 0.4845,
      "val_weighted_hit_rate": 0.48758190870521023,
      "test_n_samples": 2000,
      "test_n_directional_samples": 2000,
      "test_mae": 0.9335300284689292,
      "test_rmse": 0.9388998142895589,
      "test_r2": 0.0007054872317378003,
      "test_directional_accuracy": 0.537,
      "test_weighted_hit_rate": 0.5385805178903853,
      "diagnostics_path": "outputs\\experiment_20260416_110110\\fold_04_diagnostics.json"
    }
  ],
  "artifacts": {
    "fold_metrics_csv": "outputs\\experiment_20260416_110110\\fold_metrics.csv",
    "log": "outputs\\experiment_20260416_110110\\experiment.log"
  }
}